send_the_raven/__init__.py
send_the_raven/address.py
send_the_raven/geoaddress.py
"send_the_raven/states, cities, zipcodes.json"
send_the_raven/utils.py
send_the_raven/validator.py
send_the_raven-0.1.2.dist-info/LICENSE
send_the_raven-0.1.2.dist-info/METADATA
send_the_raven-0.1.2.dist-info/WHEEL
send_the_raven-0.1.2.dist-info/RECORD
