Metadata-Version: 2.1
Name: send-the-raven
Version: 0.1.2
Summary: A collection of toolkit and algorithms for handling US addresses
Author: Bang Koboi
Author-email: TheManHimself@jimmyganteng.com
Requires-Python: >=3.10,<4.0
Classifier: Programming Language :: Python :: 3
Classifier: Programming Language :: Python :: 3.10
Classifier: Programming Language :: Python :: 3.11
Requires-Dist: aiohttp (>=3.8.5,<4.0.0)
Requires-Dist: asyncio (>=3.4.3,<4.0.0)
Requires-Dist: geopy (>=2.4.0,<3.0.0)
Requires-Dist: h3 (>=3.7.6,<4.0.0)
Requires-Dist: pydantic (>=2.3.0,<3.0.0)
Requires-Dist: usaddress-scourgify (>=0.5.1,<0.6.0)
Requires-Dist: xmltodict (>=0.13.0,<0.14.0)
